{"blocks":{"languageVersion":0,"blocks":[{"id":"#|F%fsvCuCsd.HeYZ)74","type":"story_file","extraState":{"STORY_LINES":4},"inputs":{"STORY_LINES":{"block":{"id":"loG.F/tuUFzOB|7S#NTA","type":"_test_scene_stack","extraState":{"TEST_NAME":1},"fields":{"TEST_NAME":"vision test"},"next":{"block":{"id":"jY4hfhMSt3Lv7tOv}.dp","type":"_story_break_stack","extraState":{},"next":{"block":{"id":"hs)qYS#QdgB}4s|{#FCi","type":"_test_statement_stack","extraState":{"TEST_NAME":1,"TEST":1},"fields":{"TEST_NAME":"testing vision"},"inputs":{"TEST":{"block":{"id":"tnHLn%3^%Q=!QRK92%78","type":"test_output","extraState":{"LINES":1},"fields":{"LINES":"ok: The cabinet is dark.\nok: The cabinet has light.\nok: The cabinet is dark.\nok: The cabinet has light.\n"}}}},"next":{"block":{"id":"[V/L+goL*mQ~1=G#BvN8","type":"_test_rule_stack","extraState":{"TEST_NAME":1,"DOES":8},"fields":{"TEST_NAME":"testing vision"},"inputs":{"DOES":{"block":{"id":"=$DF4EzEp)61bERjuA!F","type":"_put_at_field_stack","extraState":{"INTO":1,"FROM":1,"AT_FIELD":1},"fields":{"AT_FIELD":"unlit"},"inputs":{"INTO":{"block":{"id":"}%K:u+(A56ud(_#|~4]$","type":"into_obj","extraState":{"OBJECT":1},"inputs":{"OBJECT":{"block":{"id":"lVYA{N8}+}UslmO4n?J1","type":"text_value","extraState":{"TEXT":1},"fields":{"TEXT":"Kitchen"}}}}}},"FROM":{"block":{"id":"UPCNWF{@l$b4be@CN.G,","type":"from_bool","extraState":{"VAL":1},"inputs":{"VAL":{"block":{"id":"`6|XsetAlqO%V!=6h?L6","type":"bool_value","extraState":{"BOOL":1},"fields":{"BOOL":true}}}}}}},"next":{"block":{"id":"^j`JPPES.}e_47LK_N.,","type":"_say_text_stack","extraState":{"TEXT":1},"inputs":{"TEXT":{"block":{"id":"_|rTq@1`bXqjzVFsOsa}","type":"render_template","extraState":{"TEMPLATE":1},"fields":{"TEMPLATE":"{if contains_light: .cabinet}ng: The cabinet has light.{else}ok: The cabinet is dark.{end}"}}}},"next":{"block":{"id":":)5hj8E;k2.@,pUzK`0W","type":"_put_at_field_stack","extraState":{"INTO":1,"FROM":1,"AT_FIELD":1},"fields":{"AT_FIELD":"lit"},"inputs":{"INTO":{"block":{"id":"O6k5Ll[]FWPF[|lVTk/x","type":"into_obj","extraState":{"OBJECT":1},"inputs":{"OBJECT":{"block":{"id":"@muT8alA]vEZw$Zo5C^X","type":"text_value","extraState":{"TEXT":1},"fields":{"TEXT":"Kitchen"}}}}}},"FROM":{"block":{"id":"8dZ.FGa8j_(/v$)w|kHe","type":"from_bool","extraState":{"VAL":1},"inputs":{"VAL":{"block":{"id":"drwoH|jm2n`yj$:V_$rx","type":"bool_value","extraState":{"BOOL":1},"fields":{"BOOL":true}}}}}}},"next":{"block":{"id":"c|~q@FvMCgNgfyL8V@ef","type":"_say_text_stack","extraState":{"TEXT":1},"inputs":{"TEXT":{"block":{"id":"BMwi5_boURI*58K)n0(T","type":"render_template","extraState":{"TEMPLATE":1},"fields":{"TEMPLATE":"{if contains_light: .cabinet}ok: The cabinet has light.{else}ng: The cabinet is dark.{end}"}}}},"next":{"block":{"id":"4z8U12CSNt_jz8xi[sHp","type":"_put_at_field_stack","extraState":{"INTO":1,"FROM":1,"AT_FIELD":1},"fields":{"AT_FIELD":"closed"},"inputs":{"INTO":{"block":{"id":"b//[75VyqJ3MT[FN_`*.","type":"into_obj","extraState":{"OBJECT":1},"inputs":{"OBJECT":{"block":{"id":"GRkIHM$*hI/Q`7rt2s0?","type":"text_value","extraState":{"TEXT":1},"fields":{"TEXT":"cabinet"}}}}}},"FROM":{"block":{"id":"Yv5c4v^D3e2{v6LK]%M}","type":"from_bool","extraState":{"VAL":1},"inputs":{"VAL":{"block":{"id":"f*FD*[6?:?Otz]ZW4I,C","type":"bool_value","extraState":{"BOOL":1},"fields":{"BOOL":true}}}}}}},"next":{"block":{"id":"RIJoP;L.98L8L=)m!Gm|","type":"_say_text_stack","extraState":{"TEXT":1},"inputs":{"TEXT":{"block":{"id":"ciri.`Z`%XsOJ%`K/{,m","type":"render_template","extraState":{"TEMPLATE":1},"fields":{"TEMPLATE":"{if contains_light: .cabinet}ng: The cabinet has light.{else}ok: The cabinet is dark.{end}"}}}},"next":{"block":{"id":";F3e$HG(gDt$_x$^[ec#","type":"_put_at_field_stack","extraState":{"INTO":1,"FROM":1,"AT_FIELD":1},"fields":{"AT_FIELD":"lit"},"inputs":{"INTO":{"block":{"id":"Xj#2)}EhH8hqa*V$P/uF","type":"into_obj","extraState":{"OBJECT":1},"inputs":{"OBJECT":{"block":{"id":":qZh[i*QkfgUwMq:Ei[m","type":"text_value","extraState":{"TEXT":1},"fields":{"TEXT":"matches"}}}}}},"FROM":{"block":{"id":"whBHX)D*vEP$=P-g*2dt","type":"from_bool","extraState":{"VAL":1},"inputs":{"VAL":{"block":{"id":"vWCvgJ7x~C::8=+Vy*u:","type":"bool_value","extraState":{"BOOL":1},"fields":{"BOOL":true}}}}}}},"next":{"block":{"id":"k$?O.01.~Qy$)Q4Hb,)A","type":"_say_text_stack","extraState":{"TEXT":1},"inputs":{"TEXT":{"block":{"id":"XkCJ3AntaUJcnhGE2]29","type":"render_template","extraState":{"TEMPLATE":1},"fields":{"TEMPLATE":"{if contains_light: .cabinet}ok: The cabinet has light.{else}ng: The cabinet is dark.{end}"}}}}}}}}}}}}}}}}}}}}}}}}}}}}}}}]}}